.dockerignore
.gitignore
.pre-commit-config.yaml
CHANGELOG.rst
Dockerfile
LICENSE
README.rst
constraints.txt
pyproject.toml
requirements.txt
setup.cfg
setup.py
tox.ini
.circleci/config.yml
debian/.gitignore
debian/build-deb.sh
src/tlwatch/__init__.py
src/tlwatch/auction_backend.py
src/tlwatch/cli.py
src/tlwatch/etherscan.py
src/tlwatch/jsonrpc.py
src/tlwatch/psql.py
src/tlwatch/relay.py
src/tlwatch/util.py
src/tlwatch/website.py
src/trustlines_watch.egg-info/PKG-INFO
src/trustlines_watch.egg-info/SOURCES.txt
src/trustlines_watch.egg-info/dependency_links.txt
src/trustlines_watch.egg-info/entry_points.txt
src/trustlines_watch.egg-info/requires.txt
src/trustlines_watch.egg-info/top_level.txt