Metadata-Version: 1.1
Name: trustlines-watch
Version: 0.5.6
Summary: monitor trustlines cluster with riemann
Home-page: https://github.com/trustlines-protocol/watch
Author: Trustlines-Network
Author-email: contact@brainbot.com
License: MIT
Platform: UNKNOWN
Classifier: Development Status :: 2 - Pre-Alpha
Classifier: Intended Audience :: Developers
Classifier: License :: OSI Approved :: MIT License
Classifier: Programming Language :: Python :: 3
Classifier: Programming Language :: Python :: 3.6
